test_step_parser/__init__.py
test_step_parser-0.0.3.dist-info/METADATA
test_step_parser-0.0.3.dist-info/WHEEL
test_step_parser-0.0.3.dist-info/top_level.txt
test_step_parser-0.0.3.dist-info/RECORD
