Metadata-Version: 2.1
Name: test-step-parser
Version: 0.0.3
Summary: The test step parser is a universal format for describing automated test steps & automatically parse source code and generate a step metadata for AI & humans to create automated tests fast and easy.
Home-page: https://qaviton.com/
Author: Yehonadav Bar Elan
Author-email: yehonadav@Qaviton.com
License: Apache 2.0
Keywords: test_step_parser
Platform: UNKNOWN
Classifier: Development Status :: 3 - Alpha
Classifier: Programming Language :: Python
Classifier: Environment :: Console
Classifier: Environment :: MacOS X
Classifier: Environment :: Win32 (MS Windows)
Classifier: Intended Audience :: Developers
Classifier: Intended Audience :: Other Audience
Classifier: License :: OSI Approved :: Apache Software License
Classifier: Operating System :: OS Independent
Classifier: Topic :: Software Development :: Quality Assurance
Classifier: Topic :: Software Development :: Testing
